fortformat/__init__.py
fortformat/fnetdata.py
fortformat/fnetout.py
fortnet_python-0.4.dist-info/LICENSE
fortnet_python-0.4.dist-info/METADATA
fortnet_python-0.4.dist-info/WHEEL
fortnet_python-0.4.dist-info/top_level.txt
fortnet_python-0.4.dist-info/RECORD
