Metadata-Version: 2.1
Name: fortnet-python
Version: 0.4
Summary: Python Tools for the Fortnet Software Package
Home-page: https://github.com/vanderhe/fortnet-python
Author: T. W. van der Heide
Author-email: vanderhe@uni-bremen.de
License: BSD
Platform: any
Classifier: Intended Audience :: Developers
Classifier: License :: OSI Approved :: BSD License
Classifier: Programming Language :: Python :: 3 :: Only
Classifier: Programming Language :: Python :: 3.7
Classifier: Programming Language :: Python :: 3.8
Classifier: Programming Language :: Python :: 3.9
Requires-Dist: ase
Requires-Dist: h5py
Requires-Dist: numpy
Requires-Dist: pytest
Requires-Dist: setuptools
Requires-Dist: wheel
